microbial/__init__.py
microbial/genomics.py
microbial/phylogeny.py
microbial/bacteria/__init__.py
microbial/bacteria/bacterium.py
microbial/fungi/__init__.py
microbial/fungi/fungus.py
microbial/viruses/__init__.py
microbial/viruses/virus.py
microbial-0.0.0.dist-info/METADATA
microbial-0.0.0.dist-info/WHEEL
microbial-0.0.0.dist-info/entry_points.txt
microbial-0.0.0.dist-info/licenses/LICENSE
microbial-0.0.0.dist-info/RECORD
