Metadata-Version: 2.4
Name: microbial
Version: 0.0.0
Summary: Add your description here
License-File: LICENSE
Requires-Python: >=3.12
Requires-Dist: biopython>=1.85
Requires-Dist: matplotlib>=3.10.3
Requires-Dist: numpy>=2.2.6
Requires-Dist: pandas>=2.2.3
Requires-Dist: seaborn>=0.13.2
